slingpy/__init__.py
slingpy/apps/__init__.py
slingpy/apps/abstract_base_application.py
slingpy/apps/app_paths.py
slingpy/apps/my_application.py
slingpy/apps/run_policies/__init__.py
slingpy/apps/run_policies/abstract_run_policy.py
slingpy/apps/run_policies/composite_run_policy.py
slingpy/apps/run_policies/cross_validation_run_policy.py
slingpy/apps/run_policies/local_single_run_policy.py
slingpy/apps/run_policies/slurm_single_run_policy.py
slingpy/apps/run_policies/hyperopt/__init__.py
slingpy/apps/run_policies/hyperopt/hyperopt_run_policy.py
slingpy/apps/run_policies/hyperopt/exploration/__init__.py
slingpy/apps/run_policies/hyperopt/exploration/abstract_exploration_strategy.py
slingpy/apps/run_policies/hyperopt/exploration/random_exploration_strategy.py
slingpy/apps/run_policies/hyperopt/exploration/sequential_exploration_strategy.py
slingpy/data_access/__init__.py
slingpy/data_access/stratified_split.py
slingpy/data_access/data_sources/__init__.py
slingpy/data_access/data_sources/abstract_data_source.py
slingpy/data_access/data_sources/composite_data_source.py
slingpy/data_access/data_sources/hdf5_data_source.py
slingpy/data_access/data_sources/hdf5_tools.py
slingpy/data_access/data_sources/torch_data_source.py
slingpy/data_access/merge_strategies/__init__.py
slingpy/data_access/merge_strategies/abstract_merge_strategy.py
slingpy/data_access/merge_strategies/concatenate_merge_strategy.py
slingpy/data_access/merge_strategies/first_entry_merge_strategy.py
slingpy/data_access/merge_strategies/mean_merge_strategy.py
slingpy/data_access/merge_strategies/no_merge_strategy.py
slingpy/data_access/merge_strategies/random_merge_strategy.py
slingpy/datasets/__init__.py
slingpy/datasets/abstract_hdf5_dataset.py
slingpy/datasets/diabetes.py
slingpy/datasets/iris.py
slingpy/evaluation/__init__.py
slingpy/evaluation/evaluator.py
slingpy/evaluation/metrics/__init__.py
slingpy/evaluation/metrics/abstract_metric.py
slingpy/evaluation/metrics/auc.py
slingpy-0.2.12.dist-info/LICENSE.txt
slingpy-0.2.12.dist-info/METADATA
slingpy-0.2.12.dist-info/WHEEL
slingpy-0.2.12.dist-info/top_level.txt
slingpy-0.2.12.dist-info/RECORD
