Metadata-Version: 2.1
Name: slingpy
Version: 0.2.12
Home-page: https://github.com/slingpy/slingpy
Author: see README.txt
Author-email: github.ps@gmail.com
License: MIT
Classifier: Programming Language :: Python :: 3
Classifier: License :: OSI Approved :: MIT License
Classifier: Operating System :: OS Independent
Requires-Python: >=3.8
License-File: LICENSE.txt
Requires-Dist: scikit-learn (>=0.22.2)
Requires-Dist: numpy (>=1.14.5)
Requires-Dist: pandas (>=1.1.5)
Requires-Dist: scipy (>=1.5.4)
Requires-Dist: h5py (>=3.0)
Requires-Dist: numba (>=0.49.0)
Requires-Dist: scikit-multilearn (>=0.2.0)
Requires-Dist: dataclasses-json (>=0.5.2)
Requires-Dist: xxhash (>=2.0.0)
Requires-Dist: torch (>=1.7.1)
Requires-Dist: requests (>=2.26.0)
Requires-Dist: ilock (>=1.0.3)
